mlflow_plugin/__init__.py
mlflow_plugin/plugin_model_rest_store.py
mlflow_plugin/plugin_rest_store.py
mlflow_asus_aimaker-1.0.2.dist-info/METADATA
mlflow_asus_aimaker-1.0.2.dist-info/WHEEL
mlflow_asus_aimaker-1.0.2.dist-info/entry_points.txt
mlflow_asus_aimaker-1.0.2.dist-info/top_level.txt
mlflow_asus_aimaker-1.0.2.dist-info/RECORD
